novu_py/__init__.py
novu_py/_hooks/__init__.py
novu_py/_hooks/novuhook.py
novu_py/_hooks/registration.py
novu_py/_hooks/sdkhooks.py
novu_py/_hooks/types.py
novu_py/_version.py
novu_py/activity.py
novu_py/basesdk.py
novu_py/channel_connections.py
novu_py/channel_endpoints.py
novu_py/contexts.py
novu_py/credentials.py
novu_py/environments.py
novu_py/groups.py
novu_py/httpclient.py
novu_py/integrations.py
novu_py/layouts.py
novu_py/master.py
novu_py/messages.py
novu_py/models/__init__.py
novu_py/models/actiondto.py
novu_py/models/activitiesresponsedto.py
novu_py/models/activitynotificationexecutiondetailresponsedto.py
novu_py/models/activitynotificationjobresponsedto.py
novu_py/models/activitynotificationresponsedto.py
novu_py/models/activitynotificationstepresponsedto.py
novu_py/models/activitynotificationsubscriberresponsedto.py
novu_py/models/activitynotificationtemplateresponsedto.py
novu_py/models/activitytopicdto.py
novu_py/models/actorfeeditemdto.py
novu_py/models/actortypeenum.py
novu_py/models/apierror.py
novu_py/models/apikeydto.py
novu_py/models/authdto.py
novu_py/models/autoconfigureintegrationresponsedto.py
novu_py/models/bridgeconfigurationdto.py
novu_py/models/builderfieldtypeenum.py
novu_py/models/bulkcreatesubscriberresponsedto.py
novu_py/models/bulksubscribercreatedto.py
novu_py/models/bulktriggereventdto.py
novu_py/models/bulkupdatesubscriberpreferenceitemdto.py
novu_py/models/bulkupdatesubscriberpreferencesdto.py
novu_py/models/buttontypeenum.py
novu_py/models/channelconnectionscontroller_createchannelconnectionop.py
novu_py/models/channelconnectionscontroller_deletechannelconnectionop.py
novu_py/models/channelconnectionscontroller_getchannelconnectionbyidentifierop.py
novu_py/models/channelconnectionscontroller_listchannelconnectionsop.py
novu_py/models/channelconnectionscontroller_updatechannelconnectionop.py
novu_py/models/channelcredentials.py
novu_py/models/channelcredentialsdto.py
novu_py/models/channelctatypeenum.py
novu_py-3.12.0.dist-info/METADATA
novu_py-3.12.0.dist-info/WHEEL
novu_py-3.12.0.dist-info/licenses/LICENSE
novu_py-3.12.0.dist-info/RECORD
